CHANGELOG.md
LICENSE
README.md
aioclamd/__init__.py
aioclamd-1.0.0.dist-info/LICENSE
aioclamd-1.0.0.dist-info/WHEEL
aioclamd-1.0.0.dist-info/METADATA
aioclamd-1.0.0.dist-info/RECORD
