Metadata-Version: 2.1
Name: aioclamd
Version: 1.0.0
Summary: Asynchronous client for virus scanning with ClamAV
Home-page: https://github.com/swedwise/aioclamd
License: MIT
Keywords: clamav,virus,scanning
Author: Henrik Blidh
Author-email: henrik.blidh@swedwise.se
Requires-Python: >=3.7,<4.0
Classifier: Development Status :: 5 - Production/Stable
Classifier: Intended Audience :: Developers
Classifier: License :: OSI Approved :: MIT License
Classifier: Operating System :: OS Independent
Classifier: Programming Language :: Python :: 3
Classifier: Programming Language :: Python :: 3.7
Classifier: Programming Language :: Python :: 3.8
Classifier: Programming Language :: Python :: 3.9
Classifier: Programming Language :: Python :: 3.10
Classifier: Programming Language :: Python :: 3
Classifier: Topic :: Software Development :: Libraries :: Python Modules
Project-URL: Repository, https://github.com/swedwise/aioclamd
